enhancer
setup.cfg
setup.py
gl_enhancer.egg-info/PKG-INFO
gl_enhancer.egg-info/SOURCES.txt
gl_enhancer.egg-info/dependency_links.txt
gl_enhancer.egg-info/requires.txt
gl_enhancer.egg-info/top_level.txt
glenhancer/__init__.py
glenhancer/enhancer.py
glenhancer/glredis.py
glenhancer/settings.py
glenhancer/utils.py
glmodule/__init__.py
glmodule/glapi.py