Metadata-Version: 1.0
Name: gl-enhancer
Version: 1.0.4
Summary: A project for Gitlab Enhancer Service (Redis)
Home-page: https://github.com/SmartDeveloperHub/gitlab-enhancer
Author: Alejandro F. Carrera
Author-email: alejandro.fernandez.carrera@centeropenmiddleware.com
License: Apache 2
Keywords: inner-source drainer enhancer
Platform: UNKNOWN
